{"cameraMode":{"drawMode":0,"name":"Shaded","section":"Shading Mode"},"sceneLighting":false,"audioPlay":false,"sceneViewState":{"m_AlwaysRefresh":false,"showFog":true,"showSkybox":false,"showFlares":true,"showImageEffects":true,"showParticleSystems":true,"showVisualEffectGraphs":true,"m_FxEnabled":true},"in2DMode":false,"pivot":{"x":0.0040292888879776,"y":1.8561688661575318,"z":-0.014847427606582642},"rotation":{"x":-0.15764714777469636,"y":0.563805103302002,"z":-0.11065412312746048,"w":-0.8031771779060364},"size":2.0014021396636965,"orthographic":false}